calc_SB.py
calc_SB-0.1.0.dist-info/WHEEL
calc_SB-0.1.0.dist-info/METADATA
calc_SB-0.1.0.dist-info/RECORD
