Metadata-Version: 2.1
Name: calc_SB
Version: 0.1.0
Summary: Calculator package
Home-page: https://github.com/cyber-zen/GTx-CS1301
Author: Simas B
Author-email: test@test.test
Classifier: License :: OSI Approved :: MIT License
